setup.cfg
setup.py
smartchoices.py
smartchoices.egg-info/PKG-INFO
smartchoices.egg-info/SOURCES.txt
smartchoices.egg-info/dependency_links.txt
smartchoices.egg-info/requires.txt
smartchoices.egg-info/top_level.txt