Metadata-Version: 1.1
Name: smartchoices
Version: 1.1
Summary: A smart choices interface for Django apps
Home-page: https://github.com/rockstar/smartchoices
Author: Paul Hummer
Author-email: paul@eventuallyanyway.com
License: MIT
Platform: UNKNOWN
Classifier: Development Status :: 5 - Production/Stable
Classifier: Environment :: Web Environment
Classifier: Intended Audience :: Developers
Classifier: License :: OSI Approved :: MIT License
Classifier: Topic :: Software Development :: Libraries :: Python Modules
